{"hms":[{"text":"0.4 Re","hm":0.4,"letter":null,"zijde":"Re","location":[5.631120285521037,52.60191601171497]},{"text":"0.2 Re","hm":0.2,"letter":null,"zijde":"Re","location":[5.63029209228244,52.60359516542766]},{"text":"0.5 Re","hm":0.5,"letter":null,"zijde":"Re","location":[5.631540848317129,52.6010791678193]},{"text":"0.6 Re","hm":0.6,"letter":null,"zijde":"Re","location":[5.631956037120506,52.600222129312904]},{"text":"0.9 Li","hm":0.9,"letter":null,"zijde":"Li","location":[5.633373198544343,52.59761549222824]},{"text":"1 Li","hm":1,"letter":null,"zijde":"Li","location":[5.633795547078648,52.59676011493729]},{"text":"0 Re","hm":0,"letter":null,"zijde":"Re","location":[5.630432603047403,52.60519470374734]},{"text":"0.1 Re","hm":0.1,"letter":null,"zijde":"Re","location":[5.630087245742343,52.60445277555815]},{"text":"0.3 Re","hm":0.3,"letter":null,"zijde":"Re","location":[5.630667601701213,52.60283262948936]},{"text":"0.8 Li","hm":0.8,"letter":null,"zijde":"Li","location":[5.632992763060749,52.59849133197281]},{"text":"1.1 Re","hm":1.1,"letter":null,"zijde":"Re","location":[5.633880354990571,52.59628398779959]},{"text":"24.4 Li","hm":24.4,"letter":null,"zijde":"Li","location":[5.56574288727446,52.16478514076201]}]}